notion_cli/__init__.py
notion_cli/client.py
notion_cli/config.py
notion_cli/filters.py
notion_cli/llm.py
notion_cli/main.py
notion_cli/notion_data.py
notion_cli/views.py
notion_cli_ai-0.1.0.dist-info/METADATA
notion_cli_ai-0.1.0.dist-info/WHEEL
notion_cli_ai-0.1.0.dist-info/entry_points.txt
notion_cli_ai-0.1.0.dist-info/licenses/LICENSE
notion_cli_ai-0.1.0.dist-info/RECORD
