Metadata-Version: 2.4
Name: notion-cli-ai
Version: 0.1.0
Summary: AI-powered CLI tool for Notion database operations using natural language
Project-URL: Homepage, https://github.com/vertexcover-io/notion-cli-ai
Project-URL: Repository, https://github.com/vertexcover-io/notion-cli-ai
Project-URL: Documentation, https://github.com/vertexcover-io/notion-cli-ai#readme
Project-URL: Bug Tracker, https://github.com/vertexcover-io/notion-cli-ai/issues
Author-email: Notion CLI AI <hello@example.com>
License-Expression: MIT
License-File: LICENSE
Keywords: ai,cli,database,llm,notion,productivity
Classifier: Development Status :: 4 - Beta
Classifier: Environment :: Console
Classifier: Intended Audience :: Developers
Classifier: Intended Audience :: End Users/Desktop
Classifier: License :: OSI Approved :: MIT License
Classifier: Operating System :: OS Independent
Classifier: Programming Language :: Python :: 3
Classifier: Programming Language :: Python :: 3.11
Classifier: Programming Language :: Python :: 3.12
Classifier: Topic :: Database
Classifier: Topic :: Office/Business
Classifier: Topic :: Scientific/Engineering :: Artificial Intelligence
Requires-Python: >=3.11
Requires-Dist: litellm>=1.0.0
Requires-Dist: notion-client>=2.2.1
Requires-Dist: platformdirs>=4.0.0
Requires-Dist: pydantic>=2.5.0
Requires-Dist: pyperclip>=1.8.0
Requires-Dist: python-dotenv>=1.0.0
Requires-Dist: requests>=2.25.0
Requires-Dist: rich>=13.0.0
Requires-Dist: toml>=0.10.2
Requires-Dist: typer>=0.9.0
